tutorial_server/__init__.py
tutorial_server/__main__.py
tutorial_server/config.py
tutorial_server/handlers.py
tutorial_server/jupyterhub_ping.py
tutorial_server/static/404.html
tutorial_server/static/503.html
tutorial_server/static/__init__.py
tutorial_server-1.0.2.dist-info/entry_points.txt
tutorial_server-1.0.2.dist-info/LICENSE
tutorial_server-1.0.2.dist-info/WHEEL
tutorial_server-1.0.2.dist-info/METADATA
tutorial_server-1.0.2.dist-info/RECORD
