Metadata-Version: 2.1
Name: tutorial-server
Version: 1.0.2
Summary: 
License: MIT
Author: Mark Hall
Author-email: mark.hall@open.ac.uk
Requires-Python: >=3.7,<4.0
Classifier: License :: OSI Approved :: MIT License
Classifier: Programming Language :: Python :: 3
Classifier: Programming Language :: Python :: 3.10
Classifier: Programming Language :: Python :: 3.7
Classifier: Programming Language :: Python :: 3.8
Classifier: Programming Language :: Python :: 3.9
Requires-Dist: filetype (>=1.0.7,<2.0.0)
Requires-Dist: tornado (>=6.1,<7.0)
